{"citeulike_paper":{"location":"http:\/\/www.citeulike.org\/user\/anonyuser2a\/article\/11527832","title":"An automatic data grabber for large web sites","abstract":"We demonstrate a system to automatically grab data from data intensive web sites. The system first infers a model that describes at the intensional level the web site as a collection of classes; each class represents a set of structurally homogeneous pages, and it is associated with a small set of representative pages. Based on the model a library of wrappers, one per class, is then inferred, with the help an external wrapper generator. The model, together with the library of wrappers, can thus be used to navigate the site and extract the data.","additional_locations":{"location":["http:\/\/portal.acm.org\/citation.cfm?id=1316824","http:\/\/www.citeulike.org\/user\/anonyuser2a\/article\/11527832","http:\/\/www.citeulike.org\/user\/anonyuser2a\/article\/11527832"]},"authors":{"author":[{"mm_name":"authors","location":"http:\/\/www.citeulike.org\/user\/anonyuser2a\/author\/Crescenzi:V","name":"Valter Crescenzi"},{"mm_name":"authors","location":"http:\/\/www.citeulike.org\/user\/anonyuser2a\/author\/Mecca:G","name":"Giansalvatore Mecca"},{"mm_name":"authors","location":"http:\/\/www.citeulike.org\/user\/anonyuser2a\/author\/Merialdo:P","name":"Paolo Merialdo"},{"mm_name":"authors","location":"http:\/\/www.citeulike.org\/user\/anonyuser2a\/author\/Missier:P","name":"Paolo Missier"}]},"source":{"mm_name":"source","title":"In Proceedings of the Thirtieth international conference on Very large data bases - Volume 30 (2004)ￂﾠ Key: citeulike:11527832"},"keywords":{"document":[{"mm_name":"keywords","location":"http:\/\/www.citeulike.org\/user\/anonyuser2a\/tag\/exp","title":"exp"},{"mm_name":"keywords","location":"http:\/\/www.citeulike.org\/user\/anonyuser2a\/tag\/new","title":"new"}]},"citeulike_user":{},"scholarly_article":{"mm_name":"source_article","title":"An automatic data grabber for large web sites"}}}